{"Lazarus_Group": "Lazarus Group", "Darkhotel": "Darkhotel", "Stolen_Pencil": "Stolen Pencil", "Cinnamon_Tempest": "Cinnamon Tempest", "Volt_Typhoon": "Volt Typhoon", "Dragonfly": "Dragonfly", "Aquatic_Panda": "Aquatic Panda", "Gamaredon_Group": "Gamaredon Group", "Nomadic_Octopus": "Nomadic Octopus", "BlackTech": "BlackTech", "BRONZE_BUTLER": "BRONZE BUTLER", "Molerats": "Molerats", "Windigo": "Windigo", "Orangeworm": "Orangeworm", "APT38": "APT38", "Moonstone_Sleet": "Moonstone Sleet", "Dust_Storm": "Dust Storm", "TA505": "TA505", "Daggerfly": "Daggerfly", "Mustang_Panda": "Mustang Panda", "Transparent_Tribe": "Transparent Tribe", "SideCopy": "SideCopy", "The_White_Company": "The White Company", "menuPass": "menuPass", "Night_Dragon": "Night Dragon", "Fox_Kitten": "Fox Kitten", "CURIUM": "CURIUM", "Cleaver": "Cleaver", "Operation_Wolf": "Operation Wolf"}